[
  {
    "id": 1,
    "username": "Tommy",
    "email": "katbak@mail.dk",
    "password": "123"
  },
  {
    "id": 2,
    "username": "Oscar",
    "email": "email@mail.dk",
    "password": "123"
  },
  {
    "id": 3,
    "username": "kasper",
    "email": "email@mail.dk",
    "password": "123"
  },
  {
    "id": 4,
    "username": "Frede",
    "email": "email@mail.dk",
    "password": "123"
  },
  {
    "id": 5,
    "username": "Jonathan",
    "email": "email@mail.dk",
    "password": "123"
  },
  {
    "id": 6,
    "username": "Karl-Emil",
    "email": "email@mail.dk",
    "password": "123"
  },
  {
    "id": 7,
    "username": "Gitte",
    "email": "email@mail.dk",
    "password": "123"
  },
  {
    "id": 8,
    "username": "Lisa",
    "email": "email@mail.dk",
    "password": "123"
  },
  {
    "id": 9,
    "username": "Michelle",
    "email": "email@mail.dk",
    "password": "123"
  },
  {
    "id": 10,
    "username": "Charlotte",
    "email": "email@mail.dk",
    "password": "123"
  },
  {
    "id": 11,
    "username": "Bente",
    "email": "email@mail.dk",
    "password": "123"
  },
  {
    "id": 12,
    "username": "Vigga",
    "email": "email@mail.dk",
    "password": "123"
  },
  {
    "id": 13,
    "username": "Sigrid",
    "email": "email@mail.dk",
    "password": "123"
  },
  {
    "id": 14,
    "username": "Brian",
    "email": "email@mail.dk",
    "password": "123"
  },
  {
    "id": 15,
    "username": "Gilbert",
    "email": "email@mail.dk",
    "password": "123"
  },
  {
    "id": 16,
    "username": "BrianJensen",
    "email": "email@mail.dk",
    "password": "123"
  },
  {
    "id": 17,
    "username": "Frederik",
    "email": "email@mail.dk",
    "password": "123"
  },
  {
    "id": 18,
    "username": "Pelle",
    "email": "email@mail.dk",
    "password": "123"
  },
  {
    "id": 19,
    "username": "Bolette",
    "email": "email@mail.dk",
    "password": "123"
  },
  {
    "id": 20,
    "username": "karlos98",
    "email": "karl@gmail.com",
    "password": "HalloDigder8"
  },
  {
    "id": 21,
    "username": "Oscar",
    "email": "os@gmail.com",
    "password": "Oscar12345"
  },
  {
    "id": 22,
    "username": "Gitte-Lis",
    "email": "gl@mail.dk",
    "password": "Kage1234"
  },
  {
    "id": 67,
    "username": "Getusercheck1",
    "email": "gl@mail.dk",
    "password": "Kage1234"
  },
  {
    "id": 125,
    "username": "Getusercheck2",
    "email": "gl@mail.dk",
    "password": "Kage1234"
  },
  {
    "id": 728,
    "username": "Viggo-Michael",
    "email": "Viggo-Michael@@xujdw0292.com",
    "password": "hdyau72..2o1n--½!!93kd"
  },
  {
    "id": 1728,
    "username": "MadsPetersen---JU288j",
    "email": "Mads Petersen@jdauj____m3333duaw.com)!",
    "password": " wandjan ajwndui228(U!/Hn873hn7/H(!? smim"
  },
  {
    "id": 172299,
    "username": "Viggo-nye2983838::juMichael",
    "email": "Viggo-Michael@@xujawudjuadw0292.com",
    "password": "hdyau72..2o1n--½!!93kd"
  },
  {
    "id": 177763,
    "username": "Mads 83e8  u33888 Petersen haha",
    "email": "Mads Petersen@jdaujduaw!!  !J8jd.com22m  i0K!)!",
    "password": " wandjan ajwndui228(U!/Hn873hn7/H(!? smim"
  },
  {
    "id": 172,
    "username": "Nybruger1",
    "email": "email1@email.com",
    "password": "123456"
  },
  {
    "id": 289,
    "username": "Nybruger2",
    "email": "email2@email.com",
    "password": "123456"
  },
  {
    "id": 18282,
    "username": "Nybruger3.--ij2iniajdam",
    "email": "email33JID2Ø-Quu@ema2QEIQil.com",
    "password": "2JIQI-_9)u/\"((JD"
  },
  {
    "id": 928928,
    "username": "Nybruger4.--ijDAOKD  IIM)#=\") 2iniajdam",
    "email": ",DMUANDA IJJI))((#@emAWMDKAWI  II22  22) =ail.com",
    "password": "E82 (u(j\" 8=i)0  U?"
  },
  {
    "id": 172,
    "username": "Nybruger1",
    "email": "email1@email.com",
    "password": "123456"
  },
  {
    "id": 289,
    "username": "Nybruger2",
    "email": "email2@email.com",
    "password": "123456"
  },
  {
    "id": 172,
    "username": "Nybruger1",
    "email": "email1@email.com",
    "password": "123456"
  },
  {
    "id": 289,
    "username": "Nybruger2",
    "email": "email2@email.com",
    "password": "123456"
  },
  {
    "id": 283477,
    "username": "getuserchecktest",
    "email": ",getuserchecktest@mail.com",
    "password": "123"
  },
  {
    "id": 289482,
    "username": "getuserchecktest2",
    "email": ",getuserchecktest2@mail.com",
    "password": "123"
  },
  {
    "id": 172,
    "username": "Nybruger1",
    "email": "email1@email.com",
    "password": "123456"
  },
  {
    "id": 289,
    "username": "Nybruger2",
    "email": "email2@email.com",
    "password": "123456"
  },
  {
    "id": 18282,
    "username": "Nybruger3.--ij2iniam",
    "email": "email33JID2Ø-Quu@ema2QEIQil.com",
    "password": "2JIQI-_9)u/\"((JD"
  },
  {
    "id": 928928,
    "username": "Nybruger4.--ijDAOKniajdam",
    "email": ",DMUANDA IJJui38IU#Uail.com",
    "password": "E82(u(j\" 8=i)0U?"
  },
  {
    "id": 18282,
    "username": "Nybruger3.--ij239 39 4¤¤iniajdam",
    "email": "email33Jm9393 772 h/)¤¤ID2Ø-Quu@ema2QEIQil.com",
    "password": "2JIQI-_9)   w_u/\"((JD"
  },
  {
    "id": 928928,
    "username": "Nybruger4.--ijDAOKD  IIM)#=\") 2iniajdam",
    "email": ",DMUANDA IJJI))((#@emAWMDKAWI  II22  22) =ail.com",
    "password": "E82 (u(j\" 8=i)0  U?"
  },
  {
    "id": 172,
    "username": "Nybruger1",
    "email": "email1@email.com",
    "password": "123456"
  },
  {
    "id": 289,
    "username": "Nybruger2",
    "email": "email2@email.com",
    "password": "123456"
  },
  {
    "id": 18282,
    "username": "Nybruger3.--ij2iniam",
    "email": "email33JID2Ø-Quu@ema2QEIQil.com",
    "password": "2JIQI-_9)u/\"((JD"
  },
  {
    "id": 928928,
    "username": "Nybruger4.--ijDAOKniajdam",
    "email": ",DMUANDA IJJui38IU#Uail.com",
    "password": "E82(u(j\" 8=i)0U?"
  },
  {
    "id": 18282,
    "username": "Nybruger3.--ij239 39 4¤¤iniajdam",
    "email": "email33Jm9393 772 h/)¤¤ID2Ø-Quu@ema2QEIQil.com",
    "password": "2JIQI-_9)   w_u/\"((JD"
  },
  {
    "id": 928928,
    "username": "Nybruger4.--ijDAOKD  IIM)#=\") 2iniajdam",
    "email": ",DMUANDA IJJI))((#@emAWMDKAWI  II22  22) =ail.com",
    "password": "E82 (u(j\" 8=i)0  U?"
  },
  {
    "id": 172,
    "username": "Nybruger1",
    "email": "email1@email.com",
    "password": "123456"
  },
  {
    "id": 289,
    "username": "Nybruger2",
    "email": "email2@email.com",
    "password": "123456"
  },
  {
    "id": 18282,
    "username": "Nybruger3.--ij2iniam",
    "email": "email33JID2Ø-Quu@ema2QEIQil.com",
    "password": "2JIQI-_9)u/\"((JD"
  },
  {
    "id": 928928,
    "username": "Nybruger4.--ijDAOKniajdam",
    "email": ",DMUANDA IJJui38IU#Uail.com",
    "password": "E82(u(j\" 8=i)0U?"
  },
  {
    "id": 18282,
    "username": "Nybruger3.--ij239 39 4¤¤iniajdam",
    "email": "email33Jm9393 772 h/)¤¤ID2Ø-Quu@ema2QEIQil.com",
    "password": "2JIQI-_9)   w_u/\"((JD"
  },
  {
    "id": 928928,
    "username": "Nybruger4.--ijDAOKD  IIM)#=\") 2iniajdam",
    "email": ",DMUANDA IJJI))((#@emAWMDKAWI  II22  22) =ail.com",
    "password": "E82 (u(j\" 8=i)0  U?"
  },
  {
    "id": 172,
    "username": "Nybruger1",
    "email": "email1@email.com",
    "password": "123456"
  },
  {
    "id": 289,
    "username": "Nybruger2",
    "email": "email2@email.com",
    "password": "123456"
  },
  {
    "id": 18282,
    "username": "Nybruger3.--ij2iniam",
    "email": "email33JID2Ø-Quu@ema2QEIQil.com",
    "password": "2JIQI-_9)u/\"((JD"
  },
  {
    "id": 928928,
    "username": "Nybruger4.--ijDAOKniajdam",
    "email": ",DMUANDA IJJui38IU#Uail.com",
    "password": "E82(u(j\" 8=i)0U?"
  },
  {
    "id": 18282,
    "username": "Nybruger3.--ij239 39 4¤¤iniajdam",
    "email": "email33Jm9393 772 h/)¤¤ID2Ø-Quu@ema2QEIQil.com",
    "password": "2JIQI-_9)   w_u/\"((JD"
  },
  {
    "id": 928928,
    "username": "Nybruger4.--ijDAOKD  IIM)#=\") 2iniajdam",
    "email": ",DMUANDA IJJI))((#@emAWMDKAWI  II22  22) =ail.com",
    "password": "E82 (u(j\" 8=i)0  U?"
  },
  {
    "id": 172,
    "username": "Nybruger1",
    "email": "email1@email.com",
    "password": "123456"
  },
  {
    "id": 289,
    "username": "Nybruger2",
    "email": "email2@email.com",
    "password": "123456"
  },
  {
    "id": 18282,
    "username": "Nybruger3.--ij2iniam",
    "email": "email33JID2Ø-Quu@ema2QEIQil.com",
    "password": "2JIQI-_9)u/\"((JD"
  },
  {
    "id": 928928,
    "username": "Nybruger4.--ijDAOKniajdam",
    "email": ",DMUANDA IJJui38IU#Uail.com",
    "password": "E82(u(j\" 8=i)0U?"
  },
  {
    "id": 18282,
    "username": "Nybruger3.--ij239 39 4¤¤iniajdam",
    "email": "email33Jm9393 772 h/)¤¤ID2Ø-Quu@ema2QEIQil.com",
    "password": "2JIQI-_9)   w_u/\"((JD"
  },
  {
    "id": 928928,
    "username": "Nybruger4.--ijDAOKD  IIM)#=\") 2iniajdam",
    "email": ",DMUANDA IJJI))((#@emAWMDKAWI  II22  22) =ail.com",
    "password": "E82 (u(j\" 8=i)0  U?"
  },
  {
    "id": 172,
    "username": "Nybruger1",
    "email": "email1@email.com",
    "password": "123456"
  },
  {
    "id": 289,
    "username": "Nybruger2",
    "email": "email2@email.com",
    "password": "123456"
  },
  {
    "id": 18282,
    "username": "Nybruger3.--ij2iniam",
    "email": "email33JID2Ø-Quu@ema2QEIQil.com",
    "password": "2JIQI-_9)u/\"((JD"
  },
  {
    "id": 928928,
    "username": "Nybruger4.--ijDAOKniajdam",
    "email": ",DMUANDA IJJui38IU#Uail.com",
    "password": "E82(u(j\" 8=i)0U?"
  },
  {
    "id": 18282,
    "username": "Nybruger3.--ij239 39 4¤¤iniajdam",
    "email": "email33Jm9393 772 h/)¤¤ID2Ø-Quu@ema2QEIQil.com",
    "password": "2JIQI-_9)   w_u/\"((JD"
  },
  {
    "id": 928928,
    "username": "Nybruger4.--ijDAOKD  IIM)#=\") 2iniajdam",
    "email": ",DMUANDA IJJI))((#@emAWMDKAWI  II22  22) =ail.com",
    "password": "E82 (u(j\" 8=i)0  U?"
  },
  {
    "id": 172,
    "username": "Nybruger1",
    "email": "email1@email.com",
    "password": "123456"
  },
  {
    "id": 289,
    "username": "Nybruger2",
    "email": "email2@email.com",
    "password": "123456"
  },
  {
    "id": 18282,
    "username": "Nybruger3.--ij2iniam",
    "email": "email33JID2Ø-Quu@ema2QEIQil.com",
    "password": "2JIQI-_9)u/\"((JD"
  },
  {
    "id": 928928,
    "username": "Nybruger4.--ijDAOKniajdam",
    "email": ",DMUANDA IJJui38IU#Uail.com",
    "password": "E82(u(j\" 8=i)0U?"
  },
  {
    "id": 18282,
    "username": "Nybruger3.--ij239 39 4¤¤iniajdam",
    "email": "email33Jm9393 772 h/)¤¤ID2Ø-Quu@ema2QEIQil.com",
    "password": "2JIQI-_9)   w_u/\"((JD"
  },
  {
    "id": 928928,
    "username": "Nybruger4.--ijDAOKD  IIM)#=\") 2iniajdam",
    "email": ",DMUANDA IJJI))((#@emAWMDKAWI  II22  22) =ail.com",
    "password": "E82 (u(j\" 8=i)0  U?"
  },
  {
    "id": 172,
    "username": "Nybruger1",
    "email": "email1@email.com",
    "password": "123456"
  },
  {
    "id": 289,
    "username": "Nybruger2",
    "email": "email2@email.com",
    "password": "123456"
  },
  {
    "id": 18282,
    "username": "Nybruger3.--ij2iniam",
    "email": "email33JID2Ø-Quu@ema2QEIQil.com",
    "password": "2JIQI-_9)u/\"((JD"
  },
  {
    "id": 928928,
    "username": "Nybruger4.--ijDAOKniajdam",
    "email": ",DMUANDA IJJui38IU#Uail.com",
    "password": "E82(u(j\" 8=i)0U?"
  },
  {
    "id": 18282,
    "username": "Nybruger3.--ij239 39 4¤¤iniajdam",
    "email": "email33Jm9393 772 h/)¤¤ID2Ø-Quu@ema2QEIQil.com",
    "password": "2JIQI-_9)   w_u/\"((JD"
  },
  {
    "id": 928928,
    "username": "Nybruger4.--ijDAOKD  IIM)#=\") 2iniajdam",
    "email": ",DMUANDA IJJI))((#@emAWMDKAWI  II22  22) =ail.com",
    "password": "E82 (u(j\" 8=i)0  U?"
  },
  {
    "id": 172,
    "username": "Nybruger1",
    "email": "email1@email.com",
    "password": "123456"
  },
  {
    "id": 289,
    "username": "Nybruger2",
    "email": "email2@email.com",
    "password": "123456"
  },
  {
    "id": 18282,
    "username": "Nybruger3.--ij2iniam",
    "email": "email33JID2Ø-Quu@ema2QEIQil.com",
    "password": "2JIQI-_9)u/\"((JD"
  },
  {
    "id": 928928,
    "username": "Nybruger4.--ijDAOKniajdam",
    "email": ",DMUANDA IJJui38IU#Uail.com",
    "password": "E82(u(j\" 8=i)0U?"
  },
  {
    "id": 18282,
    "username": "Nybruger3.--ij239 39 4¤¤iniajdam",
    "email": "email33Jm9393 772 h/)¤¤ID2Ø-Quu@ema2QEIQil.com",
    "password": "2JIQI-_9)   w_u/\"((JD"
  },
  {
    "id": 928928,
    "username": "Nybruger4.--ijDAOKD  IIM)#=\") 2iniajdam",
    "email": ",DMUANDA IJJI))((#@emAWMDKAWI  II22  22) =ail.com",
    "password": "E82 (u(j\" 8=i)0  U?"
  },
  {
    "id": 172,
    "username": "Nybruger1",
    "email": "email1@email.com",
    "password": "123456"
  },
  {
    "id": 289,
    "username": "Nybruger2",
    "email": "email2@email.com",
    "password": "123456"
  },
  {
    "id": 18282,
    "username": "Nybruger3.--ij2iniam",
    "email": "email33JID2Ø-Quu@ema2QEIQil.com",
    "password": "2JIQI-_9)u/\"((JD"
  },
  {
    "id": 928928,
    "username": "Nybruger4.--ijDAOKniajdam",
    "email": ",DMUANDA IJJui38IU#Uail.com",
    "password": "E82(u(j\" 8=i)0U?"
  },
  {
    "id": 18282,
    "username": "Nybruger3.--ij239 39 4¤¤iniajdam",
    "email": "email33Jm9393 772 h/)¤¤ID2Ø-Quu@ema2QEIQil.com",
    "password": "2JIQI-_9)   w_u/\"((JD"
  },
  {
    "id": 928928,
    "username": "Nybruger4.--ijDAOKD  IIM)#=\") 2iniajdam",
    "email": ",DMUANDA IJJI))((#@emAWMDKAWI  II22  22) =ail.com",
    "password": "E82 (u(j\" 8=i)0  U?"
  },
  {
    "id": 172,
    "username": "Nybruger1",
    "email": "email1@email.com",
    "password": "123456"
  },
  {
    "id": 289,
    "username": "Nybruger2",
    "email": "email2@email.com",
    "password": "123456"
  },
  {
    "id": 18282,
    "username": "Nybruger3.--ij2iniam",
    "email": "email33JID2Ø-Quu@ema2QEIQil.com",
    "password": "2JIQI-_9)u/\"((JD"
  },
  {
    "id": 928928,
    "username": "Nybruger4.--ijDAOKniajdam",
    "email": ",DMUANDA IJJui38IU#Uail.com",
    "password": "E82(u(j\" 8=i)0U?"
  },
  {
    "id": 18282,
    "username": "Nybruger3.--ij239 39 4¤¤iniajdam",
    "email": "email33Jm9393 772 h/)¤¤ID2Ø-Quu@ema2QEIQil.com",
    "password": "2JIQI-_9)   w_u/\"((JD"
  },
  {
    "id": 928928,
    "username": "Nybruger4.--ijDAOKD  IIM)#=\") 2iniajdam",
    "email": ",DMUANDA IJJI))((#@emAWMDKAWI  II22  22) =ail.com",
    "password": "E82 (u(j\" 8=i)0  U?"
  },
  {
    "id": 172,
    "username": "Nybruger1",
    "email": "email1@email.com",
    "password": "123456"
  },
  {
    "id": 289,
    "username": "Nybruger2",
    "email": "email2@email.com",
    "password": "123456"
  },
  {
    "id": 18282,
    "username": "Nybruger3.--ij2iniam",
    "email": "email33JID2Ø-Quu@ema2QEIQil.com",
    "password": "2JIQI-_9)u/\"((JD"
  },
  {
    "id": 928928,
    "username": "Nybruger4.--ijDAOKniajdam",
    "email": ",DMUANDA IJJui38IU#Uail.com",
    "password": "E82(u(j\" 8=i)0U?"
  },
  {
    "id": 18282,
    "username": "Nybruger3.--ij239 39 4¤¤iniajdam",
    "email": "email33Jm9393 772 h/)¤¤ID2Ø-Quu@ema2QEIQil.com",
    "password": "2JIQI-_9)   w_u/\"((JD"
  },
  {
    "id": 928928,
    "username": "Nybruger4.--ijDAOKD  IIM)#=\") 2iniajdam",
    "email": ",DMUANDA IJJI))((#@emAWMDKAWI  II22  22) =ail.com",
    "password": "E82 (u(j\" 8=i)0  U?"
  },
  {
    "id": 172,
    "username": "Nybruger1",
    "email": "email1@email.com",
    "password": "123456"
  },
  {
    "id": 289,
    "username": "Nybruger2",
    "email": "email2@email.com",
    "password": "123456"
  },
  {
    "id": 18282,
    "username": "Nybruger3.--ij2iniam",
    "email": "email33JID2Ø-Quu@ema2QEIQil.com",
    "password": "2JIQI-_9)u/\"((JD"
  },
  {
    "id": 928928,
    "username": "Nybruger4.--ijDAOKniajdam",
    "email": ",DMUANDA IJJui38IU#Uail.com",
    "password": "E82(u(j\" 8=i)0U?"
  },
  {
    "id": 18282,
    "username": "Nybruger3.--ij239 39 4¤¤iniajdam",
    "email": "email33Jm9393 772 h/)¤¤ID2Ø-Quu@ema2QEIQil.com",
    "password": "2JIQI-_9)   w_u/\"((JD"
  },
  {
    "id": 928928,
    "username": "Nybruger4.--ijDAOKD  IIM)#=\") 2iniajdam",
    "email": ",DMUANDA IJJI))((#@emAWMDKAWI  II22  22) =ail.com",
    "password": "E82 (u(j\" 8=i)0  U?"
  },
  {
    "id": 172,
    "username": "Nybruger1",
    "email": "email1@email.com",
    "password": "123456"
  },
  {
    "id": 289,
    "username": "Nybruger2",
    "email": "email2@email.com",
    "password": "123456"
  },
  {
    "id": 18282,
    "username": "Nybruger3.--ij2iniam",
    "email": "email33JID2Ø-Quu@ema2QEIQil.com",
    "password": "2JIQI-_9)u/\"((JD"
  },
  {
    "id": 928928,
    "username": "Nybruger4.--ijDAOKniajdam",
    "email": ",DMUANDA IJJui38IU#Uail.com",
    "password": "E82(u(j\" 8=i)0U?"
  },
  {
    "id": 18282,
    "username": "Nybruger3.--ij239 39 4¤¤iniajdam",
    "email": "email33Jm9393 772 h/)¤¤ID2Ø-Quu@ema2QEIQil.com",
    "password": "2JIQI-_9)   w_u/\"((JD"
  },
  {
    "id": 928928,
    "username": "Nybruger4.--ijDAOKD  IIM)#=\") 2iniajdam",
    "email": ",DMUANDA IJJI))((#@emAWMDKAWI  II22  22) =ail.com",
    "password": "E82 (u(j\" 8=i)0  U?"
  },
  {
    "id": 172,
    "username": "Nybruger1",
    "email": "email1@email.com",
    "password": "123456"
  },
  {
    "id": 289,
    "username": "Nybruger2",
    "email": "email2@email.com",
    "password": "123456"
  },
  {
    "id": 18282,
    "username": "Nybruger3.--ij2iniam",
    "email": "email33JID2Ø-Quu@ema2QEIQil.com",
    "password": "2JIQI-_9)u/\"((JD"
  },
  {
    "id": 928928,
    "username": "Nybruger4.--ijDAOKniajdam",
    "email": ",DMUANDA IJJui38IU#Uail.com",
    "password": "E82(u(j\" 8=i)0U?"
  },
  {
    "id": 18282,
    "username": "Nybruger3.--ij239 39 4¤¤iniajdam",
    "email": "email33Jm9393 772 h/)¤¤ID2Ø-Quu@ema2QEIQil.com",
    "password": "2JIQI-_9)   w_u/\"((JD"
  },
  {
    "id": 928928,
    "username": "Nybruger4.--ijDAOKD  IIM)#=\") 2iniajdam",
    "email": ",DMUANDA IJJI))((#@emAWMDKAWI  II22  22) =ail.com",
    "password": "E82 (u(j\" 8=i)0  U?"
  },
  {
    "id": 172,
    "username": "Nybruger1",
    "email": "email1@email.com",
    "password": "123456"
  },
  {
    "id": 289,
    "username": "Nybruger2",
    "email": "email2@email.com",
    "password": "123456"
  },
  {
    "id": 18282,
    "username": "Nybruger3.--ij2iniam",
    "email": "email33JID2Ø-Quu@ema2QEIQil.com",
    "password": "2JIQI-_9)u/\"((JD"
  },
  {
    "id": 928928,
    "username": "Nybruger4.--ijDAOKniajdam",
    "email": ",DMUANDA IJJui38IU#Uail.com",
    "password": "E82(u(j\" 8=i)0U?"
  },
  {
    "id": 18282,
    "username": "Nybruger3.--ij239 39 4¤¤iniajdam",
    "email": "email33Jm9393 772 h/)¤¤ID2Ø-Quu@ema2QEIQil.com",
    "password": "2JIQI-_9)   w_u/\"((JD"
  },
  {
    "id": 928928,
    "username": "Nybruger4.--ijDAOKD  IIM)#=\") 2iniajdam",
    "email": ",DMUANDA IJJI))((#@emAWMDKAWI  II22  22) =ail.com",
    "password": "E82 (u(j\" 8=i)0  U?"
  },
  {
    "id": 172,
    "username": "Nybruger1",
    "email": "email1@email.com",
    "password": "123456"
  },
  {
    "id": 289,
    "username": "Nybruger2",
    "email": "email2@email.com",
    "password": "123456"
  },
  {
    "id": 18282,
    "username": "Nybruger3.--ij2iniam",
    "email": "email33JID2Ø-Quu@ema2QEIQil.com",
    "password": "2JIQI-_9)u/\"((JD"
  },
  {
    "id": 928928,
    "username": "Nybruger4.--ijDAOKniajdam",
    "email": ",DMUANDA IJJui38IU#Uail.com",
    "password": "E82(u(j\" 8=i)0U?"
  },
  {
    "id": 18282,
    "username": "Nybruger3.--ij239 39 4¤¤iniajdam",
    "email": "email33Jm9393 772 h/)¤¤ID2Ø-Quu@ema2QEIQil.com",
    "password": "2JIQI-_9)   w_u/\"((JD"
  },
  {
    "id": 928928,
    "username": "Nybruger4.--ijDAOKD  IIM)#=\") 2iniajdam",
    "email": ",DMUANDA IJJI))((#@emAWMDKAWI  II22  22) =ail.com",
    "password": "E82 (u(j\" 8=i)0  U?"
  },
  {
    "id": 172,
    "username": "Nybruger1",
    "email": "email1@email.com",
    "password": "123456"
  },
  {
    "id": 289,
    "username": "Nybruger2",
    "email": "email2@email.com",
    "password": "123456"
  },
  {
    "id": 18282,
    "username": "Nybruger3.--ij2iniam",
    "email": "email33JID2Ø-Quu@ema2QEIQil.com",
    "password": "2JIQI-_9)u/\"((JD"
  },
  {
    "id": 928928,
    "username": "Nybruger4.--ijDAOKniajdam",
    "email": ",DMUANDA IJJui38IU#Uail.com",
    "password": "E82(u(j\" 8=i)0U?"
  },
  {
    "id": 18282,
    "username": "Nybruger3.--ij239 39 4¤¤iniajdam",
    "email": "email33Jm9393 772 h/)¤¤ID2Ø-Quu@ema2QEIQil.com",
    "password": "2JIQI-_9)   w_u/\"((JD"
  },
  {
    "id": 928928,
    "username": "Nybruger4.--ijDAOKD  IIM)#=\") 2iniajdam",
    "email": ",DMUANDA IJJI))((#@emAWMDKAWI  II22  22) =ail.com",
    "password": "E82 (u(j\" 8=i)0  U?"
  },
  {
    "id": 172,
    "username": "Nybruger1",
    "email": "email1@email.com",
    "password": "123456"
  },
  {
    "id": 289,
    "username": "Nybruger2",
    "email": "email2@email.com",
    "password": "123456"
  },
  {
    "id": 18282,
    "username": "Nybruger3.--ij2iniam",
    "email": "email33JID2Ø-Quu@ema2QEIQil.com",
    "password": "2JIQI-_9)u/\"((JD"
  },
  {
    "id": 928928,
    "username": "Nybruger4.--ijDAOKniajdam",
    "email": ",DMUANDA IJJui38IU#Uail.com",
    "password": "E82(u(j\" 8=i)0U?"
  },
  {
    "id": 18282,
    "username": "Nybruger3.--ij239 39 4¤¤iniajdam",
    "email": "email33Jm9393 772 h/)¤¤ID2Ø-Quu@ema2QEIQil.com",
    "password": "2JIQI-_9)   w_u/\"((JD"
  },
  {
    "id": 928928,
    "username": "Nybruger4.--ijDAOKD  IIM)#=\") 2iniajdam",
    "email": ",DMUANDA IJJI))((#@emAWMDKAWI  II22  22) =ail.com",
    "password": "E82 (u(j\" 8=i)0  U?"
  },
  {
    "id": 172,
    "username": "Nybruger1",
    "email": "email1@email.com",
    "password": "123456"
  },
  {
    "id": 289,
    "username": "Nybruger2",
    "email": "email2@email.com",
    "password": "123456"
  },
  {
    "id": 18282,
    "username": "Nybruger3.--ij2iniam",
    "email": "email33JID2Ø-Quu@ema2QEIQil.com",
    "password": "2JIQI-_9)u/\"((JD"
  },
  {
    "id": 928928,
    "username": "Nybruger4.--ijDAOKniajdam",
    "email": ",DMUANDA IJJui38IU#Uail.com",
    "password": "E82(u(j\" 8=i)0U?"
  },
  {
    "id": 18282,
    "username": "Nybruger3.--ij239 39 4¤¤iniajdam",
    "email": "email33Jm9393 772 h/)¤¤ID2Ø-Quu@ema2QEIQil.com",
    "password": "2JIQI-_9)   w_u/\"((JD"
  },
  {
    "id": 928928,
    "username": "Nybruger4.--ijDAOKD  IIM)#=\") 2iniajdam",
    "email": ",DMUANDA IJJI))((#@emAWMDKAWI  II22  22) =ail.com",
    "password": "E82 (u(j\" 8=i)0  U?"
  },
  {
    "id": 172,
    "username": "Nybruger1",
    "email": "email1@email.com",
    "password": "123456"
  },
  {
    "id": 289,
    "username": "Nybruger2",
    "email": "email2@email.com",
    "password": "123456"
  },
  {
    "id": 18282,
    "username": "Nybruger3.--ij2iniam",
    "email": "email33JID2Ø-Quu@ema2QEIQil.com",
    "password": "2JIQI-_9)u/\"((JD"
  },
  {
    "id": 928928,
    "username": "Nybruger4.--ijDAOKniajdam",
    "email": ",DMUANDA IJJui38IU#Uail.com",
    "password": "E82(u(j\" 8=i)0U?"
  },
  {
    "id": 18282,
    "username": "Nybruger3.--ij239 39 4¤¤iniajdam",
    "email": "email33Jm9393 772 h/)¤¤ID2Ø-Quu@ema2QEIQil.com",
    "password": "2JIQI-_9)   w_u/\"((JD"
  },
  {
    "id": 928928,
    "username": "Nybruger4.--ijDAOKD  IIM)#=\") 2iniajdam",
    "email": ",DMUANDA IJJI))((#@emAWMDKAWI  II22  22) =ail.com",
    "password": "E82 (u(j\" 8=i)0  U?"
  },
  {
    "id": 172,
    "username": "Nybruger1",
    "email": "email1@email.com",
    "password": "123456"
  },
  {
    "id": 289,
    "username": "Nybruger2",
    "email": "email2@email.com",
    "password": "123456"
  },
  {
    "id": 18282,
    "username": "Nybruger3.--ij2iniam",
    "email": "email33JID2Ø-Quu@ema2QEIQil.com",
    "password": "2JIQI-_9)u/\"((JD"
  },
  {
    "id": 928928,
    "username": "Nybruger4.--ijDAOKniajdam",
    "email": ",DMUANDA IJJui38IU#Uail.com",
    "password": "E82(u(j\" 8=i)0U?"
  },
  {
    "id": 18282,
    "username": "Nybruger3.--ij239 39 4¤¤iniajdam",
    "email": "email33Jm9393 772 h/)¤¤ID2Ø-Quu@ema2QEIQil.com",
    "password": "2JIQI-_9)   w_u/\"((JD"
  },
  {
    "id": 928928,
    "username": "Nybruger4.--ijDAOKD  IIM)#=\") 2iniajdam",
    "email": ",DMUANDA IJJI))((#@emAWMDKAWI  II22  22) =ail.com",
    "password": "E82 (u(j\" 8=i)0  U?"
  },
  {
    "id": 172,
    "username": "Nybruger1",
    "email": "email1@email.com",
    "password": "123456"
  },
  {
    "id": 289,
    "username": "Nybruger2",
    "email": "email2@email.com",
    "password": "123456"
  },
  {
    "id": 18282,
    "username": "Nybruger3.--ij2iniam",
    "email": "email33JID2Ø-Quu@ema2QEIQil.com",
    "password": "2JIQI-_9)u/\"((JD"
  },
  {
    "id": 928928,
    "username": "Nybruger4.--ijDAOKniajdam",
    "email": ",DMUANDA IJJui38IU#Uail.com",
    "password": "E82(u(j\" 8=i)0U?"
  },
  {
    "id": 18282,
    "username": "Nybruger3.--ij239 39 4¤¤iniajdam",
    "email": "email33Jm9393 772 h/)¤¤ID2Ø-Quu@ema2QEIQil.com",
    "password": "2JIQI-_9)   w_u/\"((JD"
  },
  {
    "id": 928928,
    "username": "Nybruger4.--ijDAOKD  IIM)#=\") 2iniajdam",
    "email": ",DMUANDA IJJI))((#@emAWMDKAWI  II22  22) =ail.com",
    "password": "E82 (u(j\" 8=i)0  U?"
  },
  {
    "id": 172,
    "username": "Nybruger1",
    "email": "email1@email.com",
    "password": "123456"
  },
  {
    "id": 289,
    "username": "Nybruger2",
    "email": "email2@email.com",
    "password": "123456"
  },
  {
    "id": 18282,
    "username": "Nybruger3.--ij2iniam",
    "email": "email33JID2Ø-Quu@ema2QEIQil.com",
    "password": "2JIQI-_9)u/\"((JD"
  },
  {
    "id": 928928,
    "username": "Nybruger4.--ijDAOKniajdam",
    "email": ",DMUANDA IJJui38IU#Uail.com",
    "password": "E82(u(j\" 8=i)0U?"
  },
  {
    "id": 18282,
    "username": "Nybruger3.--ij239 39 4¤¤iniajdam",
    "email": "email33Jm9393 772 h/)¤¤ID2Ø-Quu@ema2QEIQil.com",
    "password": "2JIQI-_9)   w_u/\"((JD"
  },
  {
    "id": 928928,
    "username": "Nybruger4.--ijDAOKD  IIM)#=\") 2iniajdam",
    "email": ",DMUANDA IJJI))((#@emAWMDKAWI  II22  22) =ail.com",
    "password": "E82 (u(j\" 8=i)0  U?"
  },
  {
    "id": 172,
    "username": "Nybruger1",
    "email": "email1@email.com",
    "password": "123456"
  },
  {
    "id": 289,
    "username": "Nybruger2",
    "email": "email2@email.com",
    "password": "123456"
  },
  {
    "id": 18282,
    "username": "Nybruger3.--ij2iniam",
    "email": "email33JID2Ø-Quu@ema2QEIQil.com",
    "password": "2JIQI-_9)u/\"((JD"
  },
  {
    "id": 928928,
    "username": "Nybruger4.--ijDAOKniajdam",
    "email": ",DMUANDA IJJui38IU#Uail.com",
    "password": "E82(u(j\" 8=i)0U?"
  },
  {
    "id": 18282,
    "username": "Nybruger3.--ij239 39 4¤¤iniajdam",
    "email": "email33Jm9393 772 h/)¤¤ID2Ø-Quu@ema2QEIQil.com",
    "password": "2JIQI-_9)   w_u/\"((JD"
  },
  {
    "id": 928928,
    "username": "Nybruger4.--ijDAOKD  IIM)#=\") 2iniajdam",
    "email": ",DMUANDA IJJI))((#@emAWMDKAWI  II22  22) =ail.com",
    "password": "E82 (u(j\" 8=i)0  U?"
  },
  {
    "id": 172,
    "username": "Nybruger1",
    "email": "email1@email.com",
    "password": "123456"
  },
  {
    "id": 289,
    "username": "Nybruger2",
    "email": "email2@email.com",
    "password": "123456"
  },
  {
    "id": 18282,
    "username": "Nybruger3.--ij2iniam",
    "email": "email33JID2Ø-Quu@ema2QEIQil.com",
    "password": "2JIQI-_9)u/\"((JD"
  },
  {
    "id": 928928,
    "username": "Nybruger4.--ijDAOKniajdam",
    "email": ",DMUANDA IJJui38IU#Uail.com",
    "password": "E82(u(j\" 8=i)0U?"
  },
  {
    "id": 18282,
    "username": "Nybruger3.--ij239 39 4¤¤iniajdam",
    "email": "email33Jm9393 772 h/)¤¤ID2Ø-Quu@ema2QEIQil.com",
    "password": "2JIQI-_9)   w_u/\"((JD"
  },
  {
    "id": 928928,
    "username": "Nybruger4.--ijDAOKD  IIM)#=\") 2iniajdam",
    "email": ",DMUANDA IJJI))((#@emAWMDKAWI  II22  22) =ail.com",
    "password": "E82 (u(j\" 8=i)0  U?"
  },
  {
    "id": 172,
    "username": "Nybruger1",
    "email": "email1@email.com",
    "password": "123456"
  },
  {
    "id": 289,
    "username": "Nybruger2",
    "email": "email2@email.com",
    "password": "123456"
  },
  {
    "id": 18282,
    "username": "Nybruger3.--ij2iniam",
    "email": "email33JID2Ø-Quu@ema2QEIQil.com",
    "password": "2JIQI-_9)u/\"((JD"
  },
  {
    "id": 928928,
    "username": "Nybruger4.--ijDAOKniajdam",
    "email": ",DMUANDA IJJui38IU#Uail.com",
    "password": "E82(u(j\" 8=i)0U?"
  },
  {
    "id": 18282,
    "username": "Nybruger3.--ij239 39 4¤¤iniajdam",
    "email": "email33Jm9393 772 h/)¤¤ID2Ø-Quu@ema2QEIQil.com",
    "password": "2JIQI-_9)   w_u/\"((JD"
  },
  {
    "id": 928928,
    "username": "Nybruger4.--ijDAOKD  IIM)#=\") 2iniajdam",
    "email": ",DMUANDA IJJI))((#@emAWMDKAWI  II22  22) =ail.com",
    "password": "E82 (u(j\" 8=i)0  U?"
  },
  {
    "id": 172,
    "username": "Nybruger1",
    "email": "email1@email.com",
    "password": "123456"
  },
  {
    "id": 289,
    "username": "Nybruger2",
    "email": "email2@email.com",
    "password": "123456"
  },
  {
    "id": 18282,
    "username": "Nybruger3.--ij2iniam",
    "email": "email33JID2Ø-Quu@ema2QEIQil.com",
    "password": "2JIQI-_9)u/\"((JD"
  },
  {
    "id": 928928,
    "username": "Nybruger4.--ijDAOKniajdam",
    "email": ",DMUANDA IJJui38IU#Uail.com",
    "password": "E82(u(j\" 8=i)0U?"
  },
  {
    "id": 18282,
    "username": "Nybruger3.--ij239 39 4¤¤iniajdam",
    "email": "email33Jm9393 772 h/)¤¤ID2Ø-Quu@ema2QEIQil.com",
    "password": "2JIQI-_9)   w_u/\"((JD"
  },
  {
    "id": 928928,
    "username": "Nybruger4.--ijDAOKD  IIM)#=\") 2iniajdam",
    "email": ",DMUANDA IJJI))((#@emAWMDKAWI  II22  22) =ail.com",
    "password": "E82 (u(j\" 8=i)0  U?"
  },
  {
    "id": 172,
    "username": "Nybruger1",
    "email": "email1@email.com",
    "password": "123456"
  },
  {
    "id": 289,
    "username": "Nybruger2",
    "email": "email2@email.com",
    "password": "123456"
  },
  {
    "id": 18282,
    "username": "Nybruger3.--ij2iniam",
    "email": "email33JID2Ø-Quu@ema2QEIQil.com",
    "password": "2JIQI-_9)u/\"((JD"
  },
  {
    "id": 928928,
    "username": "Nybruger4.--ijDAOKniajdam",
    "email": ",DMUANDA IJJui38IU#Uail.com",
    "password": "E82(u(j\" 8=i)0U?"
  },
  {
    "id": 18282,
    "username": "Nybruger3.--ij239 39 4¤¤iniajdam",
    "email": "email33Jm9393 772 h/)¤¤ID2Ø-Quu@ema2QEIQil.com",
    "password": "2JIQI-_9)   w_u/\"((JD"
  },
  {
    "id": 928928,
    "username": "Nybruger4.--ijDAOKD  IIM)#=\") 2iniajdam",
    "email": ",DMUANDA IJJI))((#@emAWMDKAWI  II22  22) =ail.com",
    "password": "E82 (u(j\" 8=i)0  U?"
  },
  {
    "id": 172,
    "username": "Nybruger1",
    "email": "email1@email.com",
    "password": "123456"
  },
  {
    "id": 289,
    "username": "Nybruger2",
    "email": "email2@email.com",
    "password": "123456"
  },
  {
    "id": 18282,
    "username": "Nybruger3.--ij2iniam",
    "email": "email33JID2Ø-Quu@ema2QEIQil.com",
    "password": "2JIQI-_9)u/\"((JD"
  },
  {
    "id": 928928,
    "username": "Nybruger4.--ijDAOKniajdam",
    "email": ",DMUANDA IJJui38IU#Uail.com",
    "password": "E82(u(j\" 8=i)0U?"
  },
  {
    "id": 18282,
    "username": "Nybruger3.--ij239 39 4¤¤iniajdam",
    "email": "email33Jm9393 772 h/)¤¤ID2Ø-Quu@ema2QEIQil.com",
    "password": "2JIQI-_9)   w_u/\"((JD"
  },
  {
    "id": 928928,
    "username": "Nybruger4.--ijDAOKD  IIM)#=\") 2iniajdam",
    "email": ",DMUANDA IJJI))((#@emAWMDKAWI  II22  22) =ail.com",
    "password": "E82 (u(j\" 8=i)0  U?"
  },
  {
    "id": 172,
    "username": "Nybruger1",
    "email": "email1@email.com",
    "password": "123456"
  },
  {
    "id": 289,
    "username": "Nybruger2",
    "email": "email2@email.com",
    "password": "123456"
  },
  {
    "id": 18282,
    "username": "Nybruger3.--ij2iniam",
    "email": "email33JID2Ø-Quu@ema2QEIQil.com",
    "password": "2JIQI-_9)u/\"((JD"
  },
  {
    "id": 928928,
    "username": "Nybruger4.--ijDAOKniajdam",
    "email": ",DMUANDA IJJui38IU#Uail.com",
    "password": "E82(u(j\" 8=i)0U?"
  },
  {
    "id": 18282,
    "username": "Nybruger3.--ij239 39 4¤¤iniajdam",
    "email": "email33Jm9393 772 h/)¤¤ID2Ø-Quu@ema2QEIQil.com",
    "password": "2JIQI-_9)   w_u/\"((JD"
  },
  {
    "id": 928928,
    "username": "Nybruger4.--ijDAOKD  IIM)#=\") 2iniajdam",
    "email": ",DMUANDA IJJI))((#@emAWMDKAWI  II22  22) =ail.com",
    "password": "E82 (u(j\" 8=i)0  U?"
  },
  {
    "id": 172,
    "username": "Nybruger1",
    "email": "email1@email.com",
    "password": "123456"
  },
  {
    "id": 289,
    "username": "Nybruger2",
    "email": "email2@email.com",
    "password": "123456"
  },
  {
    "id": 18282,
    "username": "Nybruger3.--ij2iniam",
    "email": "email33JID2Ø-Quu@ema2QEIQil.com",
    "password": "2JIQI-_9)u/\"((JD"
  },
  {
    "id": 928928,
    "username": "Nybruger4.--ijDAOKniajdam",
    "email": ",DMUANDA IJJui38IU#Uail.com",
    "password": "E82(u(j\" 8=i)0U?"
  },
  {
    "id": 18282,
    "username": "Nybruger3.--ij239 39 4¤¤iniajdam",
    "email": "email33Jm9393 772 h/)¤¤ID2Ø-Quu@ema2QEIQil.com",
    "password": "2JIQI-_9)   w_u/\"((JD"
  },
  {
    "id": 928928,
    "username": "Nybruger4.--ijDAOKD  IIM)#=\") 2iniajdam",
    "email": ",DMUANDA IJJI))((#@emAWMDKAWI  II22  22) =ail.com",
    "password": "E82 (u(j\" 8=i)0  U?"
  },
  {
    "id": 172,
    "username": "Nybruger1",
    "email": "email1@email.com",
    "password": "123456"
  },
  {
    "id": 289,
    "username": "Nybruger2",
    "email": "email2@email.com",
    "password": "123456"
  },
  {
    "id": 18282,
    "username": "Nybruger3.--ij2iniam",
    "email": "email33JID2Ø-Quu@ema2QEIQil.com",
    "password": "2JIQI-_9)u/\"((JD"
  },
  {
    "id": 928928,
    "username": "Nybruger4.--ijDAOKniajdam",
    "email": ",DMUANDA IJJui38IU#Uail.com",
    "password": "E82(u(j\" 8=i)0U?"
  },
  {
    "id": 18282,
    "username": "Nybruger3.--ij239 39 4¤¤iniajdam",
    "email": "email33Jm9393 772 h/)¤¤ID2Ø-Quu@ema2QEIQil.com",
    "password": "2JIQI-_9)   w_u/\"((JD"
  },
  {
    "id": 928928,
    "username": "Nybruger4.--ijDAOKD  IIM)#=\") 2iniajdam",
    "email": ",DMUANDA IJJI))((#@emAWMDKAWI  II22  22) =ail.com",
    "password": "E82 (u(j\" 8=i)0  U?"
  },
  {
    "id": 172,
    "username": "Nybruger1",
    "email": "email1@email.com",
    "password": "123456"
  },
  {
    "id": 289,
    "username": "Nybruger2",
    "email": "email2@email.com",
    "password": "123456"
  },
  {
    "id": 18282,
    "username": "Nybruger3.--ij2iniam",
    "email": "email33JID2Ø-Quu@ema2QEIQil.com",
    "password": "2JIQI-_9)u/\"((JD"
  },
  {
    "id": 928928,
    "username": "Nybruger4.--ijDAOKniajdam",
    "email": ",DMUANDA IJJui38IU#Uail.com",
    "password": "E82(u(j\" 8=i)0U?"
  },
  {
    "id": 18282,
    "username": "Nybruger3.--ij239 39 4¤¤iniajdam",
    "email": "email33Jm9393 772 h/)¤¤ID2Ø-Quu@ema2QEIQil.com",
    "password": "2JIQI-_9)   w_u/\"((JD"
  },
  {
    "id": 928928,
    "username": "Nybruger4.--ijDAOKD  IIM)#=\") 2iniajdam",
    "email": ",DMUANDA IJJI))((#@emAWMDKAWI  II22  22) =ail.com",
    "password": "E82 (u(j\" 8=i)0  U?"
  },
  {
    "id": 172,
    "username": "Nybruger1",
    "email": "email1@email.com",
    "password": "123456"
  },
  {
    "id": 289,
    "username": "Nybruger2",
    "email": "email2@email.com",
    "password": "123456"
  },
  {
    "id": 18282,
    "username": "Nybruger3.--ij2iniam",
    "email": "email33JID2Ø-Quu@ema2QEIQil.com",
    "password": "2JIQI-_9)u/\"((JD"
  },
  {
    "id": 928928,
    "username": "Nybruger4.--ijDAOKniajdam",
    "email": ",DMUANDA IJJui38IU#Uail.com",
    "password": "E82(u(j\" 8=i)0U?"
  },
  {
    "id": 18282,
    "username": "Nybruger3.--ij239 39 4¤¤iniajdam",
    "email": "email33Jm9393 772 h/)¤¤ID2Ø-Quu@ema2QEIQil.com",
    "password": "2JIQI-_9)   w_u/\"((JD"
  },
  {
    "id": 928928,
    "username": "Nybruger4.--ijDAOKD  IIM)#=\") 2iniajdam",
    "email": ",DMUANDA IJJI))((#@emAWMDKAWI  II22  22) =ail.com",
    "password": "E82 (u(j\" 8=i)0  U?"
  },
  {
    "id": 172,
    "username": "Nybruger1",
    "email": "email1@email.com",
    "password": "123456"
  },
  {
    "id": 289,
    "username": "Nybruger2",
    "email": "email2@email.com",
    "password": "123456"
  },
  {
    "id": 18282,
    "username": "Nybruger3.--ij2iniam",
    "email": "email33JID2Ø-Quu@ema2QEIQil.com",
    "password": "2JIQI-_9)u/\"((JD"
  },
  {
    "id": 928928,
    "username": "Nybruger4.--ijDAOKniajdam",
    "email": ",DMUANDA IJJui38IU#Uail.com",
    "password": "E82(u(j\" 8=i)0U?"
  },
  {
    "id": 18282,
    "username": "Nybruger3.--ij239 39 4¤¤iniajdam",
    "email": "email33Jm9393 772 h/)¤¤ID2Ø-Quu@ema2QEIQil.com",
    "password": "2JIQI-_9)   w_u/\"((JD"
  },
  {
    "id": 928928,
    "username": "Nybruger4.--ijDAOKD  IIM)#=\") 2iniajdam",
    "email": ",DMUANDA IJJI))((#@emAWMDKAWI  II22  22) =ail.com",
    "password": "E82 (u(j\" 8=i)0  U?"
  }
]